metric_dbscan/__init__.py
metric_dbscan/dbscan.py
metric_dbscan/dbscan_types.py
metric_dbscan/locator/__init__.py
metric_dbscan/locator/spatial_index.py
metric_dbscan/locator/vantage_point_tree.py
metric_dbscan/locator/wrapping.py
metric_dbscan-1.0.1.dist-info/LICENSE
metric_dbscan-1.0.1.dist-info/METADATA
metric_dbscan-1.0.1.dist-info/WHEEL
metric_dbscan-1.0.1.dist-info/RECORD
