Metadata-Version: 2.1
Name: metric-dbscan
Version: 1.0.1
Summary: DBSCAN for general metric spaces
Home-page: https://github.com/sandialabs/metric-dbscan
License: BSD-3-Clause
Keywords: clustering,dbscan,metric space
Author: Andy Wilson
Author-email: atwilso@sandia.gov
Maintainer: Andy Wilson
Maintainer-email: atwilso@sandia.gov
Requires-Python: >=3.6
Classifier: Development Status :: 5 - Production/Stable
Classifier: Intended Audience :: Science/Research
Classifier: License :: OSI Approved :: BSD License
Classifier: Programming Language :: Python
Classifier: Programming Language :: Python :: 3
Classifier: Programming Language :: Python :: 3.6
Classifier: Programming Language :: Python :: 3.7
Classifier: Programming Language :: Python :: 3.8
Classifier: Programming Language :: Python :: 3.9
Classifier: Programming Language :: Python :: 3.10
Classifier: Programming Language :: Python :: 3.11
Classifier: Programming Language :: Python :: 3.12
Classifier: Topic :: Scientific/Engineering :: Information Analysis
Requires-Dist: tqdm (>=2.0)
Project-URL: Repository, https://github.com/sandialabs/metric-dbscan
